ffdice/Dice.py
ffdice/RNG.py
ffdice/__about__.py
ffdice/__init__.py
ffdice-1.1.0.dist-info/METADATA
ffdice-1.1.0.dist-info/WHEEL
ffdice-1.1.0.dist-info/licenses/LICENSE
ffdice-1.1.0.dist-info/RECORD
