Metadata-Version: 2.1
Name: ffdice
Version: 1.1.0
Summary: A basic random number generator (RNG) that can be used for multiple purposes, such as rolling dice.
Project-URL: Homepage, https://github.com/frisfruitig/ffdice
Project-URL: Bug Tracker, https://github.com/frisfruitig/ffdice/issues
Author-email: FrisFruitig <info@frisfruitig.com>
License-File: LICENSE
Classifier: License :: OSI Approved :: MIT License
Classifier: Operating System :: OS Independent
Classifier: Programming Language :: Python :: 3
Requires-Python: >=3.6
